stocktool/__init__.py
stocktool/evaluation/__init__.py
stocktool/evaluation/evaluation.py
stocktool/model/__init__.py
stocktool/model/model.py
stocktool/visualization/__init__.py
stocktool/visualization/visualization.py
stocktool-1.1.1.dist-info/LICENSE
stocktool-1.1.1.dist-info/METADATA
stocktool-1.1.1.dist-info/WHEEL
stocktool-1.1.1.dist-info/top_level.txt
stocktool-1.1.1.dist-info/RECORD
