Metadata-Version: 2.1
Name: stocktool
Version: 1.1.1
Summary: A tool for stock price visulization and forecasting
Home-page: https://github.com/Ko2259/StockPrice
Author: Shuntao Chen, Yiling Kang
Author-email: shuntao1994@gmail.com
Project-URL: Bug Tracker, https://github.com/Ko2259/StockPrice/issues
Classifier: Programming Language :: Python :: 3
Classifier: License :: OSI Approved :: MIT License
Classifier: Operating System :: OS Independent
Requires-Python: >=3.6
License-File: LICENSE
Requires-Dist: DateTime
Requires-Dist: numpy
Requires-Dist: pandas
Requires-Dist: pandas-datareader
Requires-Dist: pandas-market-calendars
Requires-Dist: plotly
Requires-Dist: requests-cache
Requires-Dist: sktime
Requires-Dist: tbats
